MANIFEST.in
authors.txt
changes.txt
license.txt
setup.cfg
setup.py
docs/publish_notes.txt
docs/task matrix.gnumeric
pysmvt/__init__.py
pysmvt/actions.py
pysmvt/application.py
pysmvt/commands.py
pysmvt/config.py
pysmvt/controller.py
pysmvt/core.py
pysmvt/database.py
pysmvt/exceptions.py
pysmvt/htmltable.py
pysmvt/logs.py
pysmvt/mail.py
pysmvt/middleware.py
pysmvt/paster_tpl.py
pysmvt/routing.py
pysmvt/script.py
pysmvt/string.py
pysmvt/tasks.py
pysmvt/templates.py
pysmvt/test.py
pysmvt/users.py
pysmvt/view.py
pysmvt/wrappers.py
pysmvt.egg-info/PKG-INFO
pysmvt.egg-info/SOURCES.txt
pysmvt.egg-info/dependency_links.txt
pysmvt.egg-info/entry_points.txt
pysmvt.egg-info/not-zip-safe
pysmvt.egg-info/requires.txt
pysmvt.egg-info/top_level.txt
pysmvt/paster_tpls/module/__init__.py
pysmvt/paster_tpls/module/commands.py
pysmvt/paster_tpls/module/settings.py_tmpl
pysmvt/paster_tpls/module/views.py
pysmvt/paster_tpls/module/templates/index.html_tmpl
pysmvt/paster_tpls/project/MANIFEST.in_tmpl
pysmvt/paster_tpls/project/notes.txt
pysmvt/paster_tpls/project/setup.cfg
pysmvt/paster_tpls/project/setup.py_tmpl
pysmvt/paster_tpls/project/+package+/__init__.py
pysmvt/paster_tpls/project/+package+/applications.py
pysmvt/paster_tpls/project/+package+/commands.py
pysmvt/paster_tpls/project/+package+/settings.py_tmpl
pysmvt/paster_tpls/project/+package+-sharedmods/__init__.py
pysmvt/paster_tpls/project/+package+-sharedmods/modules/__init__.py
pysmvt/paster_tpls/project/+package+/modules/__init__.py
pysmvt/paster_tpls/project/+package+/modules/default/__init__.py
pysmvt/paster_tpls/project/+package+/modules/default/settings.py
pysmvt/paster_tpls/project/+package+/modules/default/views.py
pysmvt/paster_tpls/project/+package+/modules/default/templates/index.html
pysmvt/paster_tpls/project/+package+/modules/default/tests/test_functional.py_tmpl
pysmvt/paster_tpls/project/+package+/static/c/template.css
pysmvt/paster_tpls/project/+package+/templates/default.html
pysmvt/paster_tpls/project/+package+/templates/test.html
pysmvt/paster_tpls/project/tests/test_functional.py_tmpl
pysmvt/paster_tpls/project/tests/test_unit.py_tmpl
pysmvt/utils/__init__.py
pysmvt/utils/encoding.py
pysmvt/utils/filesystem.py
