Metadata-Version: 1.0
Name: pysmvt
Version: 0.2.3
Summary: A wsgi web framework with a pylons spirit and django modularity
Home-page: http://pypi.python.org/pypi/pysmvt/
Author: Randy Syring
Author-email: rsyring@gmail.com
License: BSD
Platform: UNKNOWN
Classifier: Development Status :: 4 - Beta
Classifier: Intended Audience :: Developers
Classifier: License :: OSI Approved :: BSD License
